bubble/__init__.py
bubble/constants.py
bubble/datastructures.py
bubble/debug.py
bubble/dpos.py
bubble/exceptions.py
bubble/logs.py
bubble/main.py
bubble/manager.py
bubble/method.py
bubble/module.py
bubble/net.py
bubble/node.py
bubble/pm.py
bubble/py.typed
bubble/subchain.py
bubble/tracing.py
bubble/types.py
bubble/_utils/__init__.py
bubble/_utils/abi.py
bubble/_utils/async_caching.py
bubble/_utils/async_transactions.py
bubble/_utils/blocks.py
bubble/_utils/caching.py
bubble/_utils/contracts.py
bubble/_utils/datatypes.py
bubble/_utils/decorators.py
bubble/_utils/empty.py
bubble/_utils/encoding.py
bubble/_utils/ens.py
bubble/_utils/events.py
bubble/_utils/fee_utils.py
bubble/_utils/filters.py
bubble/_utils/formatters.py
bubble/_utils/function_identifiers.py
bubble/_utils/http.py
bubble/_utils/hypothesis.py
bubble/_utils/math.py
bubble/_utils/method_formatters.py
bubble/_utils/module.py
bubble/_utils/normalizers.py
bubble/_utils/request.py
bubble/_utils/rpc_abi.py
bubble/_utils/threads.py
bubble/_utils/transactions.py
bubble/_utils/type_conversion.py
bubble/_utils/utility_methods.py
bubble/_utils/validation.py
bubble/_utils/windows.py
bubble/_utils/compat/__init__.py
bubble/_utils/compat/compat_py2.py
bubble/_utils/compat/compat_py3.py
bubble/_utils/contract_sources/__init__.py
bubble/_utils/contract_sources/compile_contracts.py
bubble/_utils/contract_sources/contract_data/__init__.py
bubble/_utils/contract_sources/contract_data/_custom_contract_data.py
bubble/_utils/contract_sources/contract_data/address_reflector.py
bubble/_utils/contract_sources/contract_data/arrays_contract.py
bubble/_utils/contract_sources/contract_data/bytes_contracts.py
bubble/_utils/contract_sources/contract_data/constructor_contracts.py
bubble/_utils/contract_sources/contract_data/contract_caller_tester.py
bubble/_utils/contract_sources/contract_data/emitter_contract.py
bubble/_utils/contract_sources/contract_data/event_contracts.py
bubble_sdk-2.1.7.dist-info/LICENSE
bubble_sdk-2.1.7.dist-info/METADATA
bubble_sdk-2.1.7.dist-info/WHEEL
bubble_sdk-2.1.7.dist-info/entry_points.txt
bubble_sdk-2.1.7.dist-info/top_level.txt
bubble_sdk-2.1.7.dist-info/RECORD
